jiracmd/__init__.py
jiracmd/jira.py
jiracmd/objects.py
jiracmd/utils.py
jiracmd/cli/__init__.py
jiracmd/cli/issue.py
jiracmd/cli/worklog.py
jiracmd-0.1.3.dist-info/LICENSE
jiracmd-0.1.3.dist-info/METADATA
jiracmd-0.1.3.dist-info/WHEEL
jiracmd-0.1.3.dist-info/entry_points.txt
jiracmd-0.1.3.dist-info/top_level.txt
jiracmd-0.1.3.dist-info/RECORD
