Metadata-Version: 2.1
Name: jiracmd
Version: 0.1.3
Summary: Jira Command Line Tool
Home-page: https://github.com/rfsantanna/jiracmd
Author: Rafael Fernandes Sant'Anna
License: Apache License, Version 2.0
Project-URL: Issues, https://github.com/rfsantanna/jiracmd/issues
Project-URL: CI, https://github.com/rfsantanna/jiracmd/actions
Project-URL: Changelog, https://github.com/rfsantanna/jiracmd/releases
Requires-Python: >=3.7
License-File: LICENSE
Requires-Dist: click
Requires-Dist: requests
Requires-Dist: tabulate
Requires-Dist: pyyaml
Provides-Extra: test
Requires-Dist: pytest ; extra == 'test'
